pandasai/__init__.py
pandasai/__version__.py
pandasai/agent/__init__.py
pandasai/agent/agent.py
pandasai/agent/base.py
pandasai/agent/base_judge.py
pandasai/agent/base_security.py
pandasai/agent/callbacks.py
pandasai/config.py
pandasai/connectors/__init__.py
pandasai/connectors/airtable.py
pandasai/connectors/base.py
pandasai/connectors/pandas.py
pandasai/connectors/polars.py
pandasai/connectors/sql.py
pandasai/connectors/yahoo_finance.py
pandasai/constants.py
pandasai/ee/LICENSE
pandasai/ee/agents/advanced_security_agent/__init__.py
pandasai/ee/agents/advanced_security_agent/pipeline/advanced_security_pipeline.py
pandasai/ee/agents/advanced_security_agent/pipeline/advanced_security_prompt_generation.py
pandasai/ee/agents/advanced_security_agent/pipeline/llm_call.py
pandasai/ee/agents/advanced_security_agent/prompts/advanced_security_agent_prompt.py
pandasai/ee/agents/advanced_security_agent/prompts/templates/advanced_security_agent_prompt.tmpl
pandasai/ee/agents/judge_agent/__init__.py
pandasai/ee/agents/judge_agent/pipeline/judge_pipeline.py
pandasai/ee/agents/judge_agent/pipeline/judge_prompt_generation.py
pandasai/ee/agents/judge_agent/pipeline/llm_call.py
pandasai/ee/agents/judge_agent/prompts/judge_agent_prompt.py
pandasai/ee/agents/judge_agent/prompts/templates/judge_agent_prompt.tmpl
pandasai/ee/agents/semantic_agent/__init__.py
pandasai/ee/agents/semantic_agent/pipeline/Semantic_prompt_generation.py
pandasai/ee/agents/semantic_agent/pipeline/code_generator.py
pandasai/ee/agents/semantic_agent/pipeline/error_correction_pipeline/error_correction_pipeline.py
pandasai/ee/agents/semantic_agent/pipeline/error_correction_pipeline/fix_semantic_json_pipeline.py
pandasai/ee/agents/semantic_agent/pipeline/error_correction_pipeline/fix_semantic_schema_prompt.py
pandasai/ee/agents/semantic_agent/pipeline/llm_call.py
pandasai/ee/agents/semantic_agent/pipeline/semantic_chat_pipeline.py
pandasai/ee/agents/semantic_agent/pipeline/semantic_result_parsing.py
pandasai-2.4.1.dist-info/LICENSE
pandasai-2.4.1.dist-info/METADATA
pandasai-2.4.1.dist-info/WHEEL
pandasai-2.4.1.dist-info/RECORD
