Metadata-Version: 2.1
Name: pandasai
Version: 2.4.1
Summary: Chat with your database (SQL, CSV, pandas, polars, mongodb, noSQL, etc). PandasAI makes data analysis conversational using LLMs (GPT 3.5 / 4, Anthropic, VertexAI) and RAG.
License: MIT
Author: Gabriele Venturi
Requires-Python: >=3.9, !=2.7.*, !=3.0.*, !=3.1.*, !=3.2.*, !=3.3.*, !=3.4.*, !=3.5.*, !=3.6.*, !=3.7.*, !=3.8.*
Classifier: License :: OSI Approved :: MIT License
Classifier: Programming Language :: Python :: 3
Classifier: Programming Language :: Python :: 3.9
Classifier: Programming Language :: Python :: 3.10
Classifier: Programming Language :: Python :: 3.11
Classifier: Programming Language :: Python :: 3.12
Classifier: Programming Language :: Python :: 3.13
Provides-Extra: bedrock
Provides-Extra: chromadb
Provides-Extra: connectors
Provides-Extra: excel
Provides-Extra: flask
Provides-Extra: ggplot
Provides-Extra: google-ai
Provides-Extra: google-sheets
Provides-Extra: ibm-watsonx-ai
Provides-Extra: lancedb
Provides-Extra: langchain
Provides-Extra: milvus
Provides-Extra: modin
Provides-Extra: numpy
Provides-Extra: pinecone
Provides-Extra: plotly
Provides-Extra: polars
Provides-Extra: qdrant
Provides-Extra: scikit-learn
Provides-Extra: seaborn
Provides-Extra: sentencec-transformers
Provides-Extra: statsmodels
Provides-Extra: streamlit
Provides-Extra: text-generation
Provides-Extra: yfinance
Requires-Dist: astor (>=0.8.1,<0.9.0)
Requires-Dist: beautifulsoup4 (>=4.12.2,<5.0.0) ; extra == "google-sheets"
Requires-Dist: boto3 (>=1.34.59) ; extra == "bedrock"
Requires-Dist: chromadb (>=0.4.22,<0.5.0) ; extra == "chromadb"
Requires-Dist: cx-Oracle (>=8.3.0,<9.0.0) ; extra == "connectors"
Requires-Dist: duckdb (>=1.0.0,<2.0.0)
Requires-Dist: faker (>=19.12.0,<20.0.0)
Requires-Dist: flask (>=3.0.2,<4.0.0) ; extra == "flask"
Requires-Dist: ggplot (>=0.11.5,<0.12.0) ; extra == "ggplot"
Requires-Dist: google-cloud-aiplatform (>=1.26.1,<2.0.0) ; extra == "google-ai"
Requires-Dist: google-generativeai (>=0.3.2,<0.4.0) ; extra == "google-ai"
Requires-Dist: ibm-watsonx-ai (>=0.2.3,<0.3.0) ; (python_version >= "3.10") and (extra == "ibm-watsonx-ai")
Requires-Dist: jinja2 (>=3.1.3,<4.0.0)
Requires-Dist: kaleido (==0.2.0) ; extra == "plotly"
Requires-Dist: lancedb (>=0.11.0,<0.12.0) ; extra == "lancedb"
Requires-Dist: langchain (>=0.1.0,<0.2.0) ; extra == "langchain"
Requires-Dist: matplotlib (>=3.7.1,<4.0.0)
Requires-Dist: milvus-model (>=0.2.7,<0.3.0) ; extra == "milvus"
Requires-Dist: modin[ray] (==0.18.1) ; extra == "modin"
Requires-Dist: numpy (>=1.17,<2.0) ; extra == "numpy"
Requires-Dist: openai (<2)
Requires-Dist: openpyxl (>=3.0.7,<4.0.0) ; extra == "excel"
Requires-Dist: pandas (==1.5.3)
Requires-Dist: pillow (>=10.1.0,<11.0.0)
Requires-Dist: pinecone-client (>=4.1.0,<5.0.0) ; (python_version >= "3.10") and (extra == "pinecone")
Requires-Dist: plotly (>=5.15.0,<6.0.0) ; extra == "plotly"
Requires-Dist: polars (>=0.18.15,<0.19.0) ; extra == "polars"
Requires-Dist: psycopg2-binary (>=2.9.7,<3.0.0) ; extra == "connectors"
Requires-Dist: pydantic (>=1,<3)
Requires-Dist: pymilvus (>=2.4.6,<3.0.0) ; extra == "milvus"
Requires-Dist: pymysql (>=1.1.0,<2.0.0) ; extra == "connectors"
Requires-Dist: python-dotenv (>=1.0.0,<2.0.0)
Requires-Dist: qdrant-client[fastembed] (>=1.11.3,<2.0.0) ; extra == "qdrant"
Requires-Dist: requests (>=2.31.0,<3.0.0)
Requires-Dist: scikit-learn (>=1.2.2,<2.0.0) ; extra == "scikit-learn"
Requires-Dist: scipy (>=1.9.0,<2.0.0)
Requires-Dist: seaborn (>=0.12.2,<0.13.0) ; extra == "seaborn"
Requires-Dist: sentence-transformers (>=2.3.0,<3.0.0) ; extra == "sentencec-transformers"
Requires-Dist: snowflake-sqlalchemy (>=1.5.0,<2.0.0) ; extra == "connectors"
Requires-Dist: sqlalchemy (>=1.4,<3)
Requires-Dist: sqlalchemy-bigquery (>=1.8.0,<2.0.0) ; (python_version >= "3.8" and python_version < "3.13") and (extra == "connectors")
Requires-Dist: sqlalchemy-cockroachdb (>=2.0.2,<3.0.0) ; extra == "connectors"
Requires-Dist: sqlalchemy-databricks (>=0.2.0,<0.3.0) ; extra == "connectors"
Requires-Dist: sqlglot[rs] (>=25.0.3,<26.0.0)
Requires-Dist: statsmodels (>=0.14.0,<0.15.0) ; extra == "statsmodels"
Requires-Dist: streamlit (>=1.23.1,<2.0.0) ; extra == "streamlit"
Requires-Dist: text-generation (>=0.6.0) ; extra == "text-generation"
Requires-Dist: torch (==2.2.0) ; sys_platform == "darwin" and platform_machine == "x86_64"
Requires-Dist: torch (==2.4.1) ; sys_platform != "darwin"
Requires-Dist: yfinance (>=0.2.28,<0.3.0) ; extra == "yfinance"
